Metadata-Version: 2.1
Name: subtrs
Version: 2.0
Summary: A simple tool that translates video subtitles
Home-page: https://gitlab.com/dslackw/subtrs
Author: Dimitris Zlatanidis
Author-email: d.zlatanidis@gmail.com
License: UNKNOWN
Keywords: video,translate,subtitles,google,youtube
Platform: UNKNOWN
Classifier: Development Status :: 5 - Production/Stable
Classifier: License :: OSI Approved :: MIT License
Classifier: Operating System :: POSIX :: Linux
Classifier: Programming Language :: Python :: 3.9
Classifier: Topic :: Text Processing
Classifier: Topic :: Terminals
Requires-Python: >=3.9
Provides-Extra: optional
Provides-Extra: docs
License-File: LICENSE.txt
